ddos_xr/__init__.py
ddos_xr/__main__.py
ddos_xr-1.0.dist-info/METADATA
ddos_xr-1.0.dist-info/WHEEL
ddos_xr-1.0.dist-info/entry_points.txt
ddos_xr-1.0.dist-info/top_level.txt
ddos_xr-1.0.dist-info/RECORD
