Metadata-Version: 2.1
Name: ddos_xr
Version: 1.0
Summary: DDos any site
Home-page: https://github.com
Author: spiderXR
License: MIT
Classifier: Programming Language :: Python :: 3
